pybpod_soundcard_module/__init__.py
pybpod_soundcard_module/module.py
pybpod_soundcard_module/module_api.py
pybpod_soundcard_module/module_gui.py
pybpod_soundcard_module/settings.py
pybpod_soundcard_module/models/__init__.py
pybpod_soundcard_module/models/projects/__init__.py
pybpod_soundcard_module/models/projects/projects_soundcard.py
pybpod_soundcard_module/resources/sound-card.png
pybpod_soundcard_module/utils/__init__.py
pybpod_soundcard_module/utils/generate_sound.py
pybpod_gui_plugin_soundcard-0.1.6.dist-info/LICENSE
pybpod_gui_plugin_soundcard-0.1.6.dist-info/METADATA
pybpod_gui_plugin_soundcard-0.1.6.dist-info/WHEEL
pybpod_gui_plugin_soundcard-0.1.6.dist-info/top_level.txt
pybpod_gui_plugin_soundcard-0.1.6.dist-info/RECORD
