Metadata-Version: 2.1
Name: pybpod-gui-plugin-soundcard
Version: 0.1.6
Summary: PyBpod Sound card module
Home-page: https://github.com/pybpod/pybpod-gui-plugin-soundcard
Author: Luís Teixeira
Author-email: micboucinha@gmail.com
License: MIT
Platform: UNKNOWN
Requires-Dist: libusb
Requires-Dist: pyusb
Requires-Dist: aenum
